kelp_o_matic/__init__.py
kelp_o_matic/config.py
kelp_o_matic/hann.py
kelp_o_matic/main.py
kelp_o_matic/model.py
kelp_o_matic/processing.py
kelp_o_matic/registry.py
kelp_o_matic/utils.py
kelp_o_matic/configs/kelp_ps8b_20250818.json
kelp_o_matic/configs/kelp_rgb_20240722.json
kelp_o_matic/configs/kelp_rgbi_20231214.json
kelp_o_matic/configs/mussel_gooseneck_rgb_20250725.json
kelp_o_matic/configs/mussel_rgb_20250711.json
kelp_o_matic-0.14.1.dist-info/METADATA
kelp_o_matic-0.14.1.dist-info/WHEEL
kelp_o_matic-0.14.1.dist-info/entry_points.txt
kelp_o_matic-0.14.1.dist-info/licenses/LICENSE
kelp_o_matic-0.14.1.dist-info/RECORD
