Metadata-Version: 2.4
Name: kelp-o-matic
Version: 0.14.1
Summary: Habitat segmentation with AI
Project-URL: Documentation, https://kelp-o-matic.readthedocs.io
Author-email: Taylor Denouden <taylor.denouden@hakai.org>
License-Expression: MIT
License-File: LICENSE
Requires-Python: >=3.10
Requires-Dist: cyclopts>=3.22.2
Requires-Dist: deprecation>=2.1.0
Requires-Dist: humanize>=4.12.3
Requires-Dist: loguru>=0.7.3
Requires-Dist: numpy>=2.2.6
Requires-Dist: onnxruntime-gpu[cuda,cudnn]>=1.22.0; platform_system != 'Darwin'
Requires-Dist: onnxruntime>=1.22.1; platform_system == 'Darwin'
Requires-Dist: opencv-python-headless>=4.11.0.86
Requires-Dist: platformdirs>=4.3.8
Requires-Dist: pydantic>=2.11.7
Requires-Dist: rasterio>=1.4.3
Requires-Dist: requests>=2.32.4
Requires-Dist: rich>=13.0.0
